{
  "version": "2.0",
  "pipeline_stage": "validated",
  "title": "Affordances of stairs",
  "description": "This dataset comprises EEG recordings and behavioral responses from participants viewing scene images and rating their aesthetic properties (beauty, complexity, interestingness) and contextual appropriateness for reading or social activities. The study investigates neural correlates of environmental perception and aesthetic judgment, with extracted behavioral data and complete stimulus set provided for reproducibility and further analysis.",
  "methods_description": "Participants viewed images of scenes and provided ratings of aesthetic properties (beauty, complexity, interestingness) and appropriateness for reading or social activities. EEG data were recorded during the task, with behavioral responses extracted from EEG events.",
  "license": "CC0",
  "dataset_type": "raw",
  "authors": {
    "Christopher Hilton": {
      "orcid": "0000-0001-9386-6935"
    },
    "Lilian Befort": {},
    "Ronja Brinkmann": {},
    "Matthias Ballestrem": {},
    "Joerg Fingerhut": {},
    "Klaus Gramann": {}
  },
  "keywords": [
    {
      "term": "EEG"
    },
    {
      "term": "aesthetic perception"
    },
    {
      "term": "environmental psychology"
    },
    {
      "term": "scene perception"
    },
    {
      "term": "behavioral responses"
    },
    {
      "term": "neuroimaging"
    }
  ],
  "related_identifiers": [
    {
      "identifier": "https://github.com/nemarDatasets/on005397",
      "identifier_type": "URL",
      "relation_type": "IsDescribedBy"
    },
    {
      "identifier": "https://nemar.org/dataexplorer/detail?dataset_id=on005397",
      "identifier_type": "URL",
      "relation_type": "IsDescribedBy"
    },
    {
      "identifier": "10.1016/j.jenvp.2025.102528",
      "identifier_type": "DOI",
      "relation_type": "IsDescribedBy"
    },
    {
      "identifier": "10.18112/openneuro.ds005397.v1.0.4",
      "identifier_type": "DOI",
      "relation_type": "IsDerivedFrom"
    }
  ],
  "resource_type_general": "Dataset",
  "resource_type_specific": "EEG Dataset",
  "modalities": [
    "eeg"
  ],
  "sizes": [
    "13.0 GB (144 files)"
  ],
  "formats": [
    ".csv",
    ".eeg",
    ".jpg",
    ".json",
    ".md",
    ".tsv",
    ".vhdr",
    ".vmrk",
    ".yml"
  ],
  "source_hash": "d4f660915505c2b70ef3106662b0779bfbb0afc95dd4708814197e8a84af350c"
}